[
  {
    "index": 1,
    "file": "001.jpg",
    "caption": "Image of Reconstruction of the Great Altar at the Ancient Greek city by ... (License: Unspecified (web source))",
    "title": "Image of Reconstruction of the Great Altar at the Ancient Greek city by ...",
    "source_url": "https://www.bridgemanimages.com/en-US/english-school/reconstruction-of-the-great-altar-at-the-ancient-greek-city-of-pergamon-asia-minor-engraving/engraving/asset/5999628",
    "query": "Pergamon Acropolis reconstruction drawing",
    "score": 17,
    "license": "Unspecified (web source)"
  },
  {
    "index": 2,
    "file": "002.jpg",
    "caption": "The Acropolis of Pergamon - TanzaAhmed - Drawings & Illustration ... (License: Unspecified (web source))",
    "title": "The Acropolis of Pergamon - TanzaAhmed - Drawings & Illustration ...",
    "source_url": "https://www.artpal.com/ahmedtanzila25?i=36375-11",
    "query": "Pergamon Acropolis reconstruction drawing",
    "score": 17,
    "license": "Unspecified (web source)"
  },
  {
    "index": 3,
    "file": "003.jpg",
    "caption": "15 best Pergamum Acropolis images by Reed Heisley-Shellaby on Pinterest ... (License: Unspecified (web source))",
    "title": "15 best Pergamum Acropolis images by Reed Heisley-Shellaby on Pinterest ...",
    "source_url": "https://www.pinterest.com/heisleyshellaby/pergamum-acropolis/",
    "query": "Pergamon Acropolis reconstruction drawing",
    "score": 14,
    "license": "Unspecified (web source)"
  },
  {
    "index": 4,
    "file": "004.jpg",
    "caption": "Acropolis of Pergamon, published in 1881 | Akropolis, Sanat, Fotoğraf (License: Unspecified (web source))",
    "title": "Acropolis of Pergamon, published in 1881 | Akropolis, Sanat, Fotoğraf",
    "source_url": "https://tr.pinterest.com/pin/visual-reconstruction-of-the-great-altar-of-pergamon-built-during--140385713367292071/",
    "query": "Pergamon Acropolis reconstruction drawing",
    "score": 14,
    "license": "Unspecified (web source)"
  },
  {
    "index": 5,
    "file": "005.jpg",
    "caption": "acropolis reconstruction plan | Acropolis, Ancient athens, Ancient ... (License: Unspecified (web source))",
    "title": "acropolis reconstruction plan | Acropolis, Ancient athens, Ancient ...",
    "source_url": "https://nl.pinterest.com/pin/721138959060206672/",
    "query": "Pergamon Acropolis reconstruction drawing",
    "score": 14,
    "license": "Unspecified (web source)"
  },
  {
    "index": 6,
    "file": "006.jpg",
    "caption": "Athena Sanctuary Pergamon - My Favourite Planet (License: Unspecified (web source))",
    "title": "Athena Sanctuary Pergamon - My Favourite Planet",
    "source_url": "http://www.my-favourite-planet.de/english/middle-east/turkey/pergamon/pergamon-photos-02-022.html",
    "query": "Pergamon Acropolis reconstruction drawing",
    "score": 14,
    "license": "Unspecified (web source)"
  },
  {
    "index": 7,
    "file": "007.jpg",
    "caption": "Exploded view of the Acropolis in Athens | Ancient greece, Ancient ... (License: Unspecified (web source))",
    "title": "Exploded view of the Acropolis in Athens | Ancient greece, Ancient ...",
    "source_url": "https://www.pinterest.com/pin/22658804348417428/",
    "query": "Pergamon Acropolis reconstruction drawing",
    "score": 14,
    "license": "Unspecified (web source)"
  },
  {
    "index": 8,
    "file": "008.jpg",
    "caption": "Image of The Acropolis at Pergamon . Turkey. Altar of Zeus. Imaginary (License: Unspecified (web source))",
    "title": "Image of The Acropolis at Pergamon . Turkey. Altar of Zeus. Imaginary",
    "source_url": "https://www.bridgemanimages.com/en-US/noartistknown/the-acropolis-at-pergamon-turkey-altar-of-zeus-imaginary-reconstruction-by-german-painter-friedrich/nomedium/asset/1109618",
    "query": "Pergamon Acropolis reconstruction drawing",
    "score": 14,
    "license": "Unspecified (web source)"
  },
  {
    "index": 9,
    "file": "009.jpg",
    "caption": "Model of the Pergamon Acropolis - My Favourite Planet (License: Unspecified (web source))",
    "title": "Model of the Pergamon Acropolis - My Favourite Planet",
    "source_url": "http://www.my-favourite-planet.de/english/middle-east/turkey/pergamon/pergamon-photos-01-004.html",
    "query": "Pergamon Acropolis reconstruction drawing",
    "score": 14,
    "license": "Unspecified (web source)"
  },
  {
    "index": 10,
    "file": "010.jpg",
    "caption": "Pergamon (License: Unspecified (web source))",
    "title": "Pergamon",
    "source_url": "https://www.anasynthesis.co.uk/index.php/pergamon",
    "query": "Pergamon Acropolis reconstruction drawing",
    "score": 14,
    "license": "Unspecified (web source)"
  },
  {
    "index": 11,
    "file": "011.jpg",
    "caption": "Pergamon (License: Unspecified (web source))",
    "title": "Pergamon",
    "source_url": "https://www.anasynthesis.co.uk/index.php/pergamon",
    "query": "Pergamon Acropolis reconstruction drawing",
    "score": 14,
    "license": "Unspecified (web source)"
  },
  {
    "index": 12,
    "file": "012.jpg",
    "caption": "Pergamon (License: Unspecified (web source))",
    "title": "Pergamon",
    "source_url": "https://www.anasynthesis.co.uk/index.php/pergamon",
    "query": "Pergamon Acropolis reconstruction drawing",
    "score": 14,
    "license": "Unspecified (web source)"
  },
  {
    "index": 13,
    "file": "013.jpg",
    "caption": "Pergamon (License: Unspecified (web source))",
    "title": "Pergamon",
    "source_url": "https://www.anasynthesis.co.uk/index.php/pergamon",
    "query": "Pergamon Acropolis reconstruction drawing",
    "score": 14,
    "license": "Unspecified (web source)"
  },
  {
    "index": 14,
    "file": "014.jpg",
    "caption": "Pergamon (License: Unspecified (web source))",
    "title": "Pergamon",
    "source_url": "https://www.anasynthesis.co.uk/index.php/pergamon",
    "query": "Pergamon Acropolis reconstruction drawing",
    "score": 14,
    "license": "Unspecified (web source)"
  },
  {
    "index": 15,
    "file": "015.jpg",
    "caption": "Pergamon - One Of 'Seven Churches Of Asia' With Great Library And ... (License: Unspecified (web source))",
    "title": "Pergamon - One Of 'Seven Churches Of Asia' With Great Library And ...",
    "source_url": "https://www.ancientpages.com/2018/07/25/intriguing-ancient-city-of-pergamon-medical-center-great-library-and-remarkable-water-supply-system/",
    "query": "Pergamon Acropolis reconstruction drawing",
    "score": 14,
    "license": "Unspecified (web source)"
  },
  {
    "index": 16,
    "file": "016.jpg",
    "caption": "Pergamon - World History Encyclopedia (License: Unspecified (web source))",
    "title": "Pergamon - World History Encyclopedia",
    "source_url": "https://www.worldhistory.org/pergamon/",
    "query": "Pergamon Acropolis reconstruction drawing",
    "score": 14,
    "license": "Unspecified (web source)"
  },
  {
    "index": 17,
    "file": "017.jpg",
    "caption": "Pergamon Ancient Theatre • Location, Photos and Information About It ... (License: Unspecified (web source))",
    "title": "Pergamon Ancient Theatre • Location, Photos and Information About It ...",
    "source_url": "https://kulturenvanteri.com/en/yer/pergamon-antik-tiyatrosu/",
    "query": "Pergamon Acropolis reconstruction drawing",
    "score": 14,
    "license": "Unspecified (web source)"
  },
  {
    "index": 18,
    "file": "018.jpg",
    "caption": "Pergamon.Pergamum.Roman.Theatre (License: Unspecified (web source))",
    "title": "Pergamon.Pergamum.Roman.Theatre",
    "source_url": "https://www.whitman.edu/theatre/theatretour/pergamum/pergamum.htm",
    "query": "Pergamon Acropolis reconstruction drawing",
    "score": 14,
    "license": "Unspecified (web source)"
  },
  {
    "index": 19,
    "file": "019.jpg",
    "caption": "Plan of Pergamon upper acropolis | Ap art history 250, Art history, Ap art (License: Unspecified (web source))",
    "title": "Plan of Pergamon upper acropolis | Ap art history 250, Art history, Ap art",
    "source_url": "https://www.pinterest.com/pin/535717318167217816/",
    "query": "Pergamon Acropolis reconstruction drawing",
    "score": 14,
    "license": "Unspecified (web source)"
  },
  {
    "index": 20,
    "file": "020.jpg",
    "caption": "Premium Photo | Majestic Ancient Greek Acropolis Reconstruction Drawing (License: Unspecified (web source))",
    "title": "Premium Photo | Majestic Ancient Greek Acropolis Reconstruction Drawing",
    "source_url": "https://www.freepik.com/premium-ai-image/majestic-ancient-greek-acropolis-reconstruction-drawing_179143777.htm",
    "query": "Pergamon Acropolis reconstruction drawing",
    "score": 14,
    "license": "Unspecified (web source)"
  },
  {
    "index": 21,
    "file": "021.jpg",
    "caption": "Propylaia Acropolis - My Favourite Planet (License: Unspecified (web source))",
    "title": "Propylaia Acropolis - My Favourite Planet",
    "source_url": "http://www.my-favourite-planet.de/english/europe/greece/attica/athens/acropolis/acropolis-photos-01-010.html",
    "query": "Pergamon Acropolis reconstruction drawing",
    "score": 14,
    "license": "Unspecified (web source)"
  },
  {
    "index": 22,
    "file": "022.jpg",
    "caption": "Reconstruction Drawing of the Acropolis Diagram | Quizlet (License: Unspecified (web source))",
    "title": "Reconstruction Drawing of the Acropolis Diagram | Quizlet",
    "source_url": "https://quizlet.com/328934859/reconstruction-drawing-of-the-acropolis-diagram/",
    "query": "Pergamon Acropolis reconstruction drawing",
    "score": 14,
    "license": "Unspecified (web source)"
  },
  {
    "index": 23,
    "file": "023.jpg",
    "caption": "Reconstruction of Pergamon Acropolis | Pergamon Museum, Berl… | Flickr (License: Unspecified (web source))",
    "title": "Reconstruction of Pergamon Acropolis | Pergamon Museum, Berl… | Flickr",
    "source_url": "https://www.flickr.com/photos/johnsylee/5348408411/",
    "query": "Pergamon Acropolis reconstruction drawing",
    "score": 14,
    "license": "Unspecified (web source)"
  },
  {
    "index": 24,
    "file": "024.jpg",
    "caption": "Smarthistory - The Pergamon Altar (License: Unspecified (web source))",
    "title": "Smarthistory - The Pergamon Altar",
    "source_url": "https://smarthistory.org/the-pergamon-altar/",
    "query": "Pergamon Acropolis reconstruction drawing",
    "score": 14,
    "license": "Unspecified (web source)"
  },
  {
    "index": 25,
    "file": "025.jpg",
    "caption": "Temple of Trajan Pergamon - My Favourite Planet (License: Unspecified (web source))",
    "title": "Temple of Trajan Pergamon - My Favourite Planet",
    "source_url": "http://www.my-favourite-planet.de/english/middle-east/turkey/pergamon/pergamon-photos-01-014.html",
    "query": "Pergamon Acropolis reconstruction drawing",
    "score": 14,
    "license": "Unspecified (web source)"
  },
  {
    "index": 26,
    "file": "026.jpg",
    "caption": "Temple of Trajan Pergamon - My Favourite Planet (License: Unspecified (web source))",
    "title": "Temple of Trajan Pergamon - My Favourite Planet",
    "source_url": "http://www.my-favourite-planet.de/english/middle-east/turkey/pergamon/pergamon-photos-01-014.html",
    "query": "Pergamon Acropolis reconstruction drawing",
    "score": 14,
    "license": "Unspecified (web source)"
  },
  {
    "index": 27,
    "file": "027.jpg",
    "caption": "The Acropolis of Pergamon - TanzaAhmed - Drawings & Illustration ... (License: Unspecified (web source))",
    "title": "The Acropolis of Pergamon - TanzaAhmed - Drawings & Illustration ...",
    "source_url": "https://www.artpal.com/ahmedtanzila25?i=36375-11",
    "query": "Pergamon Acropolis illustration",
    "score": 10,
    "license": "Unspecified (web source)"
  },
  {
    "index": 28,
    "file": "028.jpg",
    "caption": "Acropolis Of Pergamon Ancient Asia Minor Turkish History Stock ... (License: Unspecified (web source))",
    "title": "Acropolis Of Pergamon Ancient Asia Minor Turkish History Stock ...",
    "source_url": "https://www.istockphoto.com/vector/acropolis-of-pergamon-ancient-asia-minor-turkish-history-gm2191114037-609451419",
    "query": "Pergamon Acropolis illustration",
    "score": 7,
    "license": "Unspecified (web source)"
  },
  {
    "index": 29,
    "file": "029.jpg",
    "caption": "Ancient Greek city of Pergamon stock image | Look and Learn (License: Unspecified (web source))",
    "title": "Ancient Greek city of Pergamon stock image | Look and Learn",
    "source_url": "https://www.lookandlearn.com/history-images/M596564/Ancient-Greek-city-of-Pergamon",
    "query": "Pergamon Acropolis illustration",
    "score": 7,
    "license": "Unspecified (web source)"
  }
]