[
  {
    "index": 1,
    "file": "001.jpg",
    "caption": "Ancient city of Troy, illustration - Stock Image - C055/1467 - Science ... (License: Unspecified (web source)) (Expanded dataset record 0190 for Troy)",
    "title": "Ancient city of Troy, illustration - Stock Image - C055/1467 - Science ...",
    "source_url": "https://www.sciencephoto.com/media/1243088/view/ancient-city-of-troy-illustration",
    "query": "Troy ancient view",
    "score": 5,
    "license": "Unspecified (web source)"
  }
]
